deeptl/__init__.py
deeptl/plotting/__init__.py
deeptl/plotting/_heatmap.py
deeptl/plotting/_scatterplots.py
deeptl/plotting/_spatial.py
deeptl/preprocessing/__init__.py
deeptl/preprocessing/_knn.py
deeptl/preprocessing/_knn_minibatch.py
deeptl/preprocessing/_reference_centers.py
deeptl/tools/__init__.py
deeptl/tools/_deeptl.py
deeptl/tools/_deeptl_minibatch.py
deeptl/tools/_draw_graph.py
deeptl/tools/_marker_genes.py
deeptl/tools/_pathway.py
deeptl/tools/_regulons.py
deeptl/tools/_tsnep.py
sctdl-0.0.6.dist-info/WHEEL
sctdl-0.0.6.dist-info/METADATA
sctdl-0.0.6.dist-info/RECORD
