Metadata-Version: 2.1
Name: sctdl
Version: 0.0.6
Summary: 
License: MIT
Author: Lequn Wang
Author-email: wlq762@163.com
Requires-Python: >=3.7.2,<4.0
Classifier: Development Status :: 4 - Beta
Classifier: Intended Audience :: Science/Research
Classifier: License :: OSI Approved :: MIT License
Classifier: Natural Language :: English
Classifier: Operating System :: MacOS :: MacOS X
Classifier: Operating System :: Microsoft :: Windows
Classifier: Operating System :: POSIX :: Linux
Classifier: Programming Language :: Python :: 3
Classifier: Programming Language :: Python :: 3.7
Classifier: Programming Language :: Python :: 3.8
Classifier: Programming Language :: Python :: 3.9
Classifier: Topic :: Scientific/Engineering :: Bio-Informatics
Requires-Dist: anndata (>=0.7.5)
Requires-Dist: h5py (>=2.9.0)
Requires-Dist: leidenalg
Requires-Dist: numba (>=0.41.0)
Requires-Dist: numpy (>=1.17.0)
Requires-Dist: pandas (>=1.0)
Requires-Dist: pyscenic (>=0.11.0,<0.11.2)
Requires-Dist: python-igraph
Requires-Dist: scanpy (>=1.6)
Requires-Dist: scikit-learn (>=0.21.2)
Requires-Dist: scikit-misc (>=0.1.3)
Requires-Dist: torch (>=1.7.0)
Requires-Dist: tqdm (>=4.56.0)
